MANIFEST.in
README.md
setup.py
aiounfurl/__init__.py
aiounfurl/exceptions.py
aiounfurl/headers_utils.py
aiounfurl/views.py
aiounfurl.egg-info/PKG-INFO
aiounfurl.egg-info/SOURCES.txt
aiounfurl.egg-info/dependency_links.txt
aiounfurl.egg-info/not-zip-safe
aiounfurl.egg-info/requires.txt
aiounfurl.egg-info/top_level.txt
aiounfurl/__pycache__/__init__.cpython-35.pyc
aiounfurl/parsers/__init__.py
aiounfurl/parsers/meta_tags/__init__.py
aiounfurl/parsers/meta_tags/headers_tags.py
aiounfurl/parsers/meta_tags/html5_semantic_tags.py
aiounfurl/parsers/meta_tags/parser.py
aiounfurl/parsers/meta_tags/semantic_tags.py
aiounfurl/parsers/oembed/__init__.py
aiounfurl/parsers/oembed/providers_helpers.py
aiounfurl/parsers/oembed/url_extractor.py
aiounfurl/parsers/open_graph/__init__.py
aiounfurl/parsers/open_graph/parser.py
aiounfurl/parsers/twitter_cards/__init__.py
aiounfurl/parsers/twitter_cards/parser.py