Metadata-Version: 1.1
Name: aiounfurl
Version: 0.2.4
Summary: Making site preview
Home-page: https://github.com/tigorc/aiounfurl
Author: Igor Tokarev
Author-email: TigorC@gmail.com
License: BSD License
Keywords: async embed preview
Platform: UNKNOWN
Classifier: Development Status :: 4 - Beta
Classifier: Intended Audience :: Developers
Classifier: License :: OSI Approved :: BSD License
Classifier: Programming Language :: Python
Classifier: Programming Language :: Python :: 3.5
Classifier: Programming Language :: Python :: 3 :: Only
Classifier: Topic :: Internet :: WWW/HTTP
